{
    "fluentMethods": true,
    "clientRootFolder": "",
    "relationships": [],
    "fields": [
        {
            "fieldName": "name",
            "fieldType": "String"
        },
        {
            "fieldName": "lactureHall",
            "fieldType": "String"
        }
    ],
    "changelogDate": "20190326130155",
    "dto": "mapstruct",
    "searchEngine": false,
    "service": "serviceImpl",
    "entityTableName": "classrooms",
    "databaseType": "sql",
    "jpaMetamodelFiltering": false,
    "pagination": "no"
}
